genx/_genx
genx
